addition/__init__.py
addition/add.py
division/__init__.py
division/divide.py
multiplication/__init__.py
multiplication/multiply.py
substraction/__init__.py
substraction/substract.py
lody_calc_package-0.0.1.dist-info/LICENCE.txt
lody_calc_package-0.0.1.dist-info/METADATA
lody_calc_package-0.0.1.dist-info/WHEEL
lody_calc_package-0.0.1.dist-info/top_level.txt
lody_calc_package-0.0.1.dist-info/RECORD
