Metadata-Version: 2.1
Name: lody-calc-package
Version: 0.0.1
Summary: A calculator package
Home-page: https://github.com/lodyne/lody_calc_package
Author: lodyne
Author-email: lodgmtui@gmail.com
Project-URL: Package builder, https://github.com/lodyne/lody_calc_package
Classifier: Programming Language :: Python :: 3
Classifier: License :: OSI Approved :: MIT License
Classifier: Operating System :: OS Independent
Requires-Python: >=3.6
License-File: LICENCE.txt
